nmalign/__init__.py
nmalign/lib/__init__.py
nmalign/lib/align.py
nmalign/ocrd/__init__.py
nmalign/ocrd/cli.py
nmalign/ocrd/ocrd-tool.json
nmalign/scripts/__init__.py
nmalign/scripts/cli.py
nmalign-0.0.5.dist-info/METADATA
nmalign-0.0.5.dist-info/WHEEL
nmalign-0.0.5.dist-info/entry_points.txt
nmalign-0.0.5.dist-info/top_level.txt
nmalign-0.0.5.dist-info/RECORD
