Metadata-Version: 2.1
Name: nmalign
Version: 0.0.5
Summary: forced alignment of lists of string by fuzzy string matching
Author-email: Robert Sachunsky <sachunsky@informatik.uni-leipzig.de>
License: MIT
Project-URL: Homepage, https://github.com/bertsky/nmalign
Project-URL: Repository, https://github.com/bertsky/nmalign.git
Classifier: Development Status :: 5 - Production/Stable
Classifier: Environment :: Console
Classifier: Intended Audience :: Science/Research
Classifier: Intended Audience :: Other Audience
Classifier: License :: OSI Approved :: MIT License
Classifier: Programming Language :: Python :: 3
Classifier: Programming Language :: Python :: 3 :: Only
Classifier: Topic :: Text Processing
Requires-Python: >=3.8
Requires-Dist: rapidfuzz>=2.0
Requires-Dist: numpy
Requires-Dist: scipy
Requires-Dist: click
Requires-Dist: cloup
Requires-Dist: ocrd
Requires-Dist: joblib
